{
  "realm": "eventhub",
  "enabled": true,
  "registrationAllowed": true,
  "loginWithEmailAllowed": true,
  "duplicateEmailsAllowed": false,
  "resetPasswordAllowed": true,
  "roles": {
    "realm": [
      { "name": "user", "description": "Authenticated event attendee" },
      { "name": "organizer", "description": "Event organizer" },
      { "name": "admin", "description": "Platform administrator" }
    ]
  },
  "clients": [
    {
      "clientId": "eventhub-frontend",
      "name": "EventHub Angular Frontend",
      "enabled": true,
      "protocol": "openid-connect",
      "publicClient": true,
      "standardFlowEnabled": true,
      "directAccessGrantsEnabled": true,
      "implicitFlowEnabled": false,
      "redirectUris": [
        "http://localhost:4200/*",
        "https://laughing-journey-q766xwpqqwrh45j-4200.app.github.dev/*"
      ],
      "webOrigins": [
        "http://localhost:4200",
        "https://laughing-journey-q766xwpqqwrh45j-4200.app.github.dev"
      ],
      "attributes": {
        "pkce.code.challenge.method": "S256",
        "post.logout.redirect.uris": "+"
      }
    },
    {
      "clientId": "eventhub-admin",
      "name": "EventHub Backend Admin Client",
      "enabled": true,
      "protocol": "openid-connect",
      "publicClient": false,
      "secret": "4eJdFKPX5uOWabkZJ5OiiedzgjXApnHa",
      "serviceAccountsEnabled": true,
      "standardFlowEnabled": false,
      "directAccessGrantsEnabled": false,
      "implicitFlowEnabled": false
    }
  ],
  "users": [
    {
      "username": "service-account-eventhub-admin",
      "enabled": true,
      "serviceAccountClientId": "eventhub-admin",
      "clientRoles": {
        "realm-management": [
          "manage-users",
          "view-users",
          "view-realm"
        ]
      }
    }
  ]
}
